{"inkVersion":21,"root":[["^Life is full of choices, and every decision you make can affect your future. How do you decide what's the right choice?","\n",["ev",{"^->":"0.2.$r1"},{"temp=":"$r"},"str",{"->":".^.s"},[{"#n":"$r1"}],"/str","/ev",{"*":"0.c-0","flg":18},{"s":["^I weigh the pros and cons before making a decision.",{"->":"$r","var":true},null]}],["ev",{"^->":"0.3.$r1"},{"temp=":"$r"},"str",{"->":".^.s"},[{"#n":"$r1"}],"/str","/ev",{"*":"0.c-1","flg":18},{"s":["^I follow my instincts, even if it’s risky.",{"->":"$r","var":true},null]}],["ev",{"^->":"0.4.$r1"},{"temp=":"$r"},"str",{"->":".^.s"},[{"#n":"$r1"}],"/str","/ev",{"*":"0.c-2","flg":18},{"s":["^I don’t think much about it, I just go with the flow.",{"->":"$r","var":true},null]}],{"c-0":["ev",{"^->":"0.c-0.$r2"},"/ev",{"temp=":"$r"},{"->":"0.2.s"},[{"#n":"$r2"}],"\n",{"->":"Weighing_Pros_Cons"},{"->":"0.g-0"},{"#f":5}],"c-1":["ev",{"^->":"0.c-1.$r2"},"/ev",{"temp=":"$r"},{"->":"0.3.s"},[{"#n":"$r2"}],"\n",{"->":"Follow_Instincts"},{"->":"0.g-0"},{"#f":5}],"c-2":["ev",{"^->":"0.c-2.$r2"},"/ev",{"temp=":"$r"},{"->":"0.4.s"},[{"#n":"$r2"}],"\n",{"->":"Go_With_Flow"},{"->":"0.g-0"},{"#f":5}],"g-0":["done",{"#f":5}]}],"done",{"Weighing_Pros_Cons":[["^Teacher: That’s a wise approach. Thinking carefully helps avoid regret. Do you have any recent decisions you’re proud of?","\n",["ev",{"^->":"Weighing_Pros_Cons.0.2.$r1"},{"temp=":"$r"},"str",{"->":".^.s"},[{"#n":"$r1"}],"/str","/ev",{"*":".^.^.c-0","flg":18},{"s":["^I decided to focus more on my studies.",{"->":"$r","var":true},null]}],["ev",{"^->":"Weighing_Pros_Cons.0.3.$r1"},{"temp=":"$r"},"str",{"->":".^.s"},[{"#n":"$r1"}],"/str","/ev",{"*":".^.^.c-1","flg":18},{"s":["^I chose to spend more time helping my family.",{"->":"$r","var":true},null]}],{"c-0":["ev",{"^->":"Weighing_Pros_Cons.0.c-0.$r2"},"/ev",{"temp=":"$r"},{"->":".^.^.2.s"},[{"#n":"$r2"}],"\n",{"->":"Focus_Studies"},{"#f":5}],"c-1":["ev",{"^->":"Weighing_Pros_Cons.0.c-1.$r2"},"/ev",{"temp=":"$r"},{"->":".^.^.3.s"},[{"#n":"$r2"}],"\n",{"->":"Help_Family"},{"#f":5}]}],{"#f":1}],"Focus_Studies":["^Teacher: That’s great. Education can open so many opportunities if you dedicate yourself to it.","\n","end",{"#f":1}],"Help_Family":["^Teacher: Helping family is important. Balancing your responsibilities shows maturity.","\n","end",{"#f":1}],"Follow_Instincts":[["^Teacher: Following your instincts can lead to interesting experiences, but it’s important to balance it with reason. Have you made any risky choices recently?","\n",["ev",{"^->":"Follow_Instincts.0.2.$r1"},{"temp=":"$r"},"str",{"->":".^.s"},[{"#n":"$r1"}],"/str","/ev",{"*":".^.^.c-0","flg":18},{"s":["^Yes, and it ended up working out well.",{"->":"$r","var":true},null]}],["ev",{"^->":"Follow_Instincts.0.3.$r1"},{"temp=":"$r"},"str",{"->":".^.s"},[{"#n":"$r1"}],"/str","/ev",{"*":".^.^.c-1","flg":18},{"s":["^Yes, but it didn’t turn out the way I wanted.",{"->":"$r","var":true},null]}],{"c-0":["ev",{"^->":"Follow_Instincts.0.c-0.$r2"},"/ev",{"temp=":"$r"},{"->":".^.^.2.s"},[{"#n":"$r2"}],"\n",{"->":"Risk_Worked"},{"#f":5}],"c-1":["ev",{"^->":"Follow_Instincts.0.c-1.$r2"},"/ev",{"temp=":"$r"},{"->":".^.^.3.s"},[{"#n":"$r2"}],"\n",{"->":"Risk_Failed"},{"#f":5}]}],{"#f":1}],"Risk_Worked":["^Teacher: Sometimes taking risks can lead to rewards. Just remember to weigh the consequences carefully.","\n","end",{"#f":1}],"Risk_Failed":["^Teacher: It’s okay to make mistakes. We learn the most from our failures.","\n","end",{"#f":1}],"Go_With_Flow":[["^Teacher: Going with the flow is easy, but without direction, you may end up somewhere you didn’t want to be. Have you considered planning more?","\n",["ev",{"^->":"Go_With_Flow.0.2.$r1"},{"temp=":"$r"},"str",{"->":".^.s"},[{"#n":"$r1"}],"/str","/ev",{"*":".^.^.c-0","flg":18},{"s":["^I think I should start making more plans.",{"->":"$r","var":true},null]}],["ev",{"^->":"Go_With_Flow.0.3.$r1"},{"temp=":"$r"},"str",{"->":".^.s"},[{"#n":"$r1"}],"/str","/ev",{"*":".^.^.c-1","flg":18},{"s":["^I’m okay with seeing where life takes me.",{"->":"$r","var":true},null]}],{"c-0":["ev",{"^->":"Go_With_Flow.0.c-0.$r2"},"/ev",{"temp=":"$r"},{"->":".^.^.2.s"},[{"#n":"$r2"}],"\n",{"->":"Start_Planning"},{"#f":5}],"c-1":["ev",{"^->":"Go_With_Flow.0.c-1.$r2"},"/ev",{"temp=":"$r"},{"->":".^.^.3.s"},[{"#n":"$r2"}],"\n",{"->":"No_Plans"},{"#f":5}]}],{"#f":1}],"Start_Planning":["^Teacher: Planning doesn’t guarantee success, but it does help you stay prepared for challenges. It’s worth trying.","\n","end",{"#f":1}],"No_Plans":["^Teacher: Just be careful that you don’t drift too far from where you want to be. A little planning can go a long way.","\n","end",{"#f":1}],"#f":1}],"listDefs":{}}