{"inkVersion":21,"root":[["\n","^Hier in die Flats, jy moet hustle vir alles. Niemand gee jou niks nie. Hoe’s jou hustle game?","\n",["ev",{"^->":"0.3.$r1"},{"temp=":"$r"},"str",{"->":".^.s"},[{"#n":"$r1"}],"/str","/ev",{"*":"0.c-0","flg":18},{"s":["^I’m working hard, trying to make something of myself.",{"->":"$r","var":true},null]}],["ev",{"^->":"0.4.$r1"},{"temp=":"$r"},"str",{"->":".^.s"},[{"#n":"$r1"}],"/str","/ev",{"*":"0.c-1","flg":18},{"s":["^I hustle hard, but I take what I want.",{"->":"$r","var":true},null]}],["ev",{"^->":"0.5.$r1"},{"temp=":"$r"},"str",{"->":".^.s"},[{"#n":"$r1"}],"/str","/ev",{"*":"0.c-2","flg":18},{"s":["^I don’t know what my hustle is yet.",{"->":"$r","var":true},null]}],{"c-0":["ev",{"^->":"0.c-0.$r2"},"/ev",{"temp=":"$r"},{"->":"0.3.s"},[{"#n":"$r2"}],"\n",{"->":"Working_Hard"},{"->":"0.g-0"},{"#f":5}],"c-1":["ev",{"^->":"0.c-1.$r2"},"/ev",{"temp=":"$r"},{"->":"0.4.s"},[{"#n":"$r2"}],"\n",{"->":"Take_What_I_Want"},{"->":"0.g-0"},{"#f":5}],"c-2":["ev",{"^->":"0.c-2.$r2"},"/ev",{"temp=":"$r"},{"->":"0.5.s"},[{"#n":"$r2"}],"\n",{"->":"Dont_Know_Hustle"},{"->":"0.g-0"},{"#f":5}],"g-0":["done",{"#f":5}]}],"done",{"Working_Hard":[["^Aweh, bru, just onthou die hustle never stop. Jy moet stay busy, anders die streets gaan kry jou.","\n",["ev",{"^->":"Working_Hard.0.2.$r1"},{"temp=":"$r"},"str",{"->":".^.s"},[{"#n":"$r1"}],"/str","/ev",{"*":".^.^.c-0","flg":18},{"s":["^I’m doing what I can.",{"->":"$r","var":true},null]}],["ev",{"^->":"Working_Hard.0.3.$r1"},{"temp=":"$r"},"str",{"->":".^.s"},[{"#n":"$r1"}],"/str","/ev",{"*":".^.^.c-1","flg":18},{"s":["^I’m not sure if I’m hustling enough.",{"->":"$r","var":true},null]}],{"c-0":["ev",{"^->":"Working_Hard.0.c-0.$r2"},"/ev",{"temp=":"$r"},{"->":".^.^.2.s"},[{"#n":"$r2"}],"\n",{"->":"Doing_What_I_Can"},{"#f":5}],"c-1":["ev",{"^->":"Working_Hard.0.c-1.$r2"},"/ev",{"temp=":"$r"},{"->":".^.^.3.s"},[{"#n":"$r2"}],"\n",{"->":"Not_Sure_Hustling_Enough"},{"#f":5}]}],{"#f":1}],"Doing_What_I_Can":["^Good. Just don’t let up, bru.","\n",{"->":"AddEdu"},"end",{"#f":1}],"Not_Sure_Hustling_Enough":["^Daai’s dangerous. If jy slack, die life gaan leave jou behind.","\n","end",{"#f":1}],"Take_What_I_Want":[["^Ja, maar jy better watch jou back, bru. Jy vat too much, people gaan come for you.","\n","^\"Imagine jy’re at die **old warehouse** with a chance to take some valuable supplies. Would jy take it, knowing it might bring trouble?\"","\n",["ev",{"^->":"Take_What_I_Want.0.4.$r1"},{"temp=":"$r"},"str",{"->":".^.s"},[{"#n":"$r1"}],"/str","/ev",{"*":".^.^.c-0","flg":18},{"s":["^I’ll take it. I’m not scared of the risks.",{"->":"$r","var":true},null]}],["ev",{"^->":"Take_What_I_Want.0.5.$r1"},{"temp=":"$r"},"str",{"->":".^.s"},[{"#n":"$r1"}],"/str","/ev",{"*":".^.^.c-1","flg":18},{"s":["^No, I’ll wait for a better time.",{"->":"$r","var":true},null]}],{"c-0":["ev",{"^->":"Take_What_I_Want.0.c-0.$r2"},"/ev",{"temp=":"$r"},{"->":".^.^.4.s"},[{"#n":"$r2"}],"\n",{"->":"AddGang"},"^Gang Leader: \"Aweh, jy praat mos. But onthou, die Flats gaan onthou jou actions.\"","\n",{"->":"Hustle_Task_Complete"},{"#f":5}],"c-1":["ev",{"^->":"Take_What_I_Want.0.c-1.$r2"},"/ev",{"temp=":"$r"},{"->":".^.^.5.s"},[{"#n":"$r2"}],"\n",{"->":"AddEdu"},"^Gang Leader: \"Slim move. Patience is also part van die hustle game, my bru.\"","\n",{"->":"Hustle_Task_Complete"},{"#f":5}]}],{"#f":1}],"Hustle_Task_Complete":["^Gang Leader: \"Remember, bru, jy hustle defines jou future. Maak seker jy balance dit reg.\"","\n","end",{"#f":1}],"Dont_Know_Hustle":[["^Jy better find dit vinnig, bru. Die Flats gaan mos nie wait for jy nie.","\n",["ev",{"^->":"Dont_Know_Hustle.0.2.$r1"},{"temp=":"$r"},"str",{"->":".^.s"},[{"#n":"$r1"}],"/str","/ev",{"*":".^.^.c-0","flg":18},{"s":["^I’ll figure it out soon.",{"->":"$r","var":true},null]}],["ev",{"^->":"Dont_Know_Hustle.0.3.$r1"},{"temp=":"$r"},"str",{"->":".^.s"},[{"#n":"$r1"}],"/str","/ev",{"*":".^.^.c-1","flg":18},{"s":["^Maybe hustling isn’t for me.",{"->":"$r","var":true},null]}],{"c-0":["ev",{"^->":"Dont_Know_Hustle.0.c-0.$r2"},"/ev",{"temp=":"$r"},{"->":".^.^.2.s"},[{"#n":"$r2"}],"\n",{"->":"Figure_It_Out_Soon"},{"#f":5}],"c-1":["ev",{"^->":"Dont_Know_Hustle.0.c-1.$r2"},"/ev",{"temp=":"$r"},{"->":".^.^.3.s"},[{"#n":"$r2"}],"\n",{"->":"Hustling_Not_For_Me"},{"#f":5}]}],{"#f":1}],"Figure_It_Out_Soon":["^Make sure jy do. Jy gaan nodig hê daai hustle.","\n","end",{"#f":1}],"Hustling_Not_For_Me":["^Jy better think again. Jy kan’t survive hier sonder hustle.","\n","end",{"#f":1}],"AddEdu":["ev",{"VAR?":"EduStat"},1,"+",{"VAR=":"EduStat","re":true},"/ev","ev",{"VAR?":"GangStat"},1,"-",0,"MAX","/ev",{"VAR=":"GangStat","re":true},"\n","end",{"#f":1}],"AddGang":["ev",{"VAR?":"GangStat"},1,"+",{"VAR=":"GangStat","re":true},"/ev","ev",{"VAR?":"EduStat"},1,"-",0,"MAX","/ev",{"VAR=":"EduStat","re":true},"\n","end",{"#f":1}],"global decl":["ev",0,{"VAR=":"EduStat"},0,{"VAR=":"GangStat"},false,{"VAR=":"teacherQuestStarted"},false,{"VAR=":"teacherQuestCompleted"},false,{"VAR=":"gangQuestStarted"},false,{"VAR=":"gangQuestCompleted"},"/ev","end",null],"#f":1}],"listDefs":{}}