{"inkVersion":21,"root":[["\n","^On die Flats, jy moet take control van jou life, bru, or die streets gaan control jou. Hoe gaan jy daai handle?","\n",["ev",{"^->":"0.3.$r1"},{"temp=":"$r"},"str",{"->":".^.s"},[{"#n":"$r1"}],"/str","/ev",{"*":"0.c-0","flg":18},{"s":["^I’m taking control of my future.",{"->":"$r","var":true},null]}],["ev",{"^->":"0.4.$r1"},{"temp=":"$r"},"str",{"->":".^.s"},[{"#n":"$r1"}],"/str","/ev",{"*":"0.c-1","flg":18},{"s":["^I’ll take control, no matter the cost.",{"->":"$r","var":true},null]}],["ev",{"^->":"0.5.$r1"},{"temp=":"$r"},"str",{"->":".^.s"},[{"#n":"$r1"}],"/str","/ev",{"*":"0.c-2","flg":18},{"s":["^I don’t care about control.",{"->":"$r","var":true},null]}],{"c-0":["ev",{"^->":"0.c-0.$r2"},"/ev",{"temp=":"$r"},{"->":"0.3.s"},[{"#n":"$r2"}],"\n",{"->":"Taking_Control_Of_Future"},{"->":"0.g-0"},{"#f":5}],"c-1":["ev",{"^->":"0.c-1.$r2"},"/ev",{"temp=":"$r"},{"->":"0.4.s"},[{"#n":"$r2"}],"\n",{"->":"Control_At_Any_Cost"},{"->":"0.g-0"},{"#f":5}],"c-2":["ev",{"^->":"0.c-2.$r2"},"/ev",{"temp=":"$r"},{"->":"0.5.s"},[{"#n":"$r2"}],"\n",{"->":"Dont_Care_About_Control"},{"->":"0.g-0"},{"#f":5}],"g-0":["done",{"#f":5}]}],"done",{"Taking_Control_Of_Future":[["^Aweh, dis ‘n goeie move, maar onthou, die Flats gaan test jou.","\n",["ev",{"^->":"Taking_Control_Of_Future.0.2.$r1"},{"temp=":"$r"},"str",{"->":".^.s"},[{"#n":"$r1"}],"/str","/ev",{"*":".^.^.c-0","flg":18},{"s":["^I’m ready for the test.",{"->":"$r","var":true},null]}],["ev",{"^->":"Taking_Control_Of_Future.0.3.$r1"},{"temp=":"$r"},"str",{"->":".^.s"},[{"#n":"$r1"}],"/str","/ev",{"*":".^.^.c-1","flg":18},{"s":["^I’m not sure how to take control yet.",{"->":"$r","var":true},null]}],{"c-0":["ev",{"^->":"Taking_Control_Of_Future.0.c-0.$r2"},"/ev",{"temp=":"$r"},{"->":".^.^.2.s"},[{"#n":"$r2"}],"\n",{"->":"Ready_For_Test"},{"#f":5}],"c-1":["ev",{"^->":"Taking_Control_Of_Future.0.c-1.$r2"},"/ev",{"temp=":"$r"},{"->":".^.^.3.s"},[{"#n":"$r2"}],"\n",{"->":"Unsure_About_Control"},{"#f":5}]}],{"#f":1}],"Ready_For_Test":["^Good. Just onthou, control is nie permanent nie.","\n",{"->":"AddEdu"},"end",{"#f":1}],"Unsure_About_Control":["^Jy gaan need to learn vinnig, bru. Die Flats gaan nie wait for jou nie.","\n","end",{"#f":1}],"Control_At_Any_Cost":[["^Ja, maar onthou, bru, control is nie always worth die cost.","\n",["ev",{"^->":"Control_At_Any_Cost.0.2.$r1"},{"temp=":"$r"},"str",{"->":".^.s"},[{"#n":"$r1"}],"/str","/ev",{"*":".^.^.c-0","flg":18},{"s":["^I’ll deal with whatever comes.",{"->":"$r","var":true},null]}],{"c-0":["ev",{"^->":"Control_At_Any_Cost.0.c-0.$r2"},"/ev",{"temp=":"$r"},{"->":".^.^.2.s"},[{"#n":"$r2"}],"\n",{"->":"Deal_With_Cost"},{"#f":5}]}],{"#f":1}],"Deal_With_Cost":["^Ons gaan sien, maar jy gaan feel daai cost vinnig.","\n",{"->":"AddGang"},"end",{"#f":1}],"Dont_Care_About_Control":[["^Jy gaan care when die Flats push jou around. Jy moet fight vir jou life.","\n",["ev",{"^->":"Dont_Care_About_Control.0.2.$r1"},{"temp=":"$r"},"str",{"->":".^.s"},[{"#n":"$r1"}],"/str","/ev",{"*":".^.^.c-0","flg":18},{"s":["^We’ll see.",{"->":"$r","var":true},null]}],{"c-0":["ev",{"^->":"Dont_Care_About_Control.0.c-0.$r2"},"/ev",{"temp=":"$r"},{"->":".^.^.2.s"},[{"#n":"$r2"}],"\n",{"->":"See_About_Control"},{"#f":5}]}],{"#f":1}],"See_About_Control":["^Ja, ons gaan sien.","\n","end",{"#f":1}],"AddEdu":["ev",{"VAR?":"EduStat"},1,"+",{"VAR=":"EduStat","re":true},"/ev","ev",{"VAR?":"GangStat"},1,"-",0,"MIN","/ev",{"VAR=":"GangStat","re":true},"\n","end",{"#f":1}],"AddGang":["ev",{"VAR?":"GangStat"},1,"+",{"VAR=":"GangStat","re":true},"/ev","ev",{"VAR?":"EduStat"},1,"-",0,"MIN","/ev",{"VAR=":"EduStat","re":true},"\n","end",{"#f":1}],"global decl":["ev",0,{"VAR=":"EduStat"},0,{"VAR=":"GangStat"},false,{"VAR=":"supportQuestStarted"},false,{"VAR=":"dreamsQuestStarted"},false,{"VAR=":"honestyQuestStarted"},false,{"VAR=":"familyQuestStarted"},false,{"VAR=":"roleModelQuestStarted"},false,{"VAR=":"trustQuestCompleted"},false,{"VAR=":"choicesQuestStarted"},false,{"VAR=":"gangQuestStarted"},false,{"VAR=":"gangQuestCompleted"},false,{"VAR=":"influenceQuestStarted"},false,{"VAR=":"troubleQuestStarted"},false,{"VAR=":"standingFirmQuestStarted"},false,{"VAR=":"teacherQuestStarted"},false,{"VAR=":"teacherQuestCompleted"},false,{"VAR=":"studyMentorSpawned"},false,{"VAR=":"empathyQuestStarted"},false,{"VAR=":"empathyQuestCompleted"},false,{"VAR=":"emotionalQuestCompleted"},false,{"VAR=":"timeManagementQuestCompleted"},false,{"VAR=":"teacherPriorityQuestCompleted"},false,{"VAR=":"teacherPriorityQuestStarted"},false,{"VAR=":"teacherGoalQuestStarted"},false,{"VAR=":"teacherGoalQuestCompleted"},false,{"VAR=":"conflictResolutionQuestStarted"},false,{"VAR=":"conflictResolutionQuestCompleted"},false,{"VAR=":"lifeChoicesQuestStarted"},false,{"VAR=":"lifeChoicesQuestCompleted"},false,{"VAR=":"healthyChoicesQuestStarted"},false,{"VAR=":"healthyChoicesQuestCompleted"},false,{"VAR=":"constructiveCriticismQuestStarted"},false,{"VAR=":"constructiveCriticismQuestCompleted"},false,{"VAR=":"smallWinsQuestStarted"},false,{"VAR=":"smallWinsQuestCompleted"},false,{"VAR=":"stayFocusedQuestStarted"},false,{"VAR=":"stayFocusedQuestCompleted"},false,{"VAR=":"communityQuestStarted"},false,{"VAR=":"communityQuestCompleted"},"/ev","end",null],"#f":1}],"listDefs":{}}