{"inkVersion":21,"root":[["\n","^Do you know why education matters? It’s not just about passing tests. It’s about building your future, giving yourself options. Do you understand that?","\n",["ev",{"^->":"0.3.$r1"},{"temp=":"$r"},"str",{"->":".^.s"},[{"#n":"$r1"}],"/str","/ev",{"*":"0.c-0","flg":18},{"s":["^I get it, miss. I’m trying to focus and learn as much as I can.",{"->":"$r","var":true},null]}],["ev",{"^->":"0.4.$r1"},{"temp=":"$r"},"str",{"->":".^.s"},[{"#n":"$r1"}],"/str","/ev",{"*":"0.c-1","flg":18},{"s":["^Honestly, it feels like a waste of time sometimes.",{"->":"$r","var":true},null]}],["ev",{"^->":"0.5.$r1"},{"temp=":"$r"},"str",{"->":".^.s"},[{"#n":"$r1"}],"/str","/ev",{"*":"0.c-2","flg":18},{"s":["^I understand it’s important, but it’s hard to stay motivated.",{"->":"$r","var":true},null]}],{"c-0":["ev",{"^->":"0.c-0.$r2"},"/ev",{"temp=":"$r"},{"->":"0.3.s"},[{"#n":"$r2"}],"\n",{"->":"I_Get_It"},{"->":"0.g-0"},{"#f":5}],"c-1":["ev",{"^->":"0.c-1.$r2"},"/ev",{"temp=":"$r"},{"->":"0.4.s"},[{"#n":"$r2"}],"\n",{"->":"Waste_Of_Time"},{"->":"0.g-0"},{"#f":5}],"c-2":["ev",{"^->":"0.c-2.$r2"},"/ev",{"temp=":"$r"},{"->":"0.5.s"},[{"#n":"$r2"}],"\n",{"->":"Hard_To_Stay_Motivated"},{"->":"0.g-0"},{"#f":5}],"g-0":["done",{"#f":5}]}],"done",{"I_Get_It":[["^Good. Focus will take you far. What are you enjoying most about your studies?","\n",["ev",{"^->":"I_Get_It.0.2.$r1"},{"temp=":"$r"},"str",{"->":".^.s"},[{"#n":"$r1"}],"/str","/ev",{"*":".^.^.c-0","flg":18},{"s":["^Math, because it feels like it’s building a foundation for my future.",{"->":"$r","var":true},null]}],["ev",{"^->":"I_Get_It.0.3.$r1"},{"temp=":"$r"},"str",{"->":".^.s"},[{"#n":"$r1"}],"/str","/ev",{"*":".^.^.c-1","flg":18},{"s":["^I’m still figuring it out, but I’m doing my best.",{"->":"$r","var":true},null]}],{"c-0":["ev",{"^->":"I_Get_It.0.c-0.$r2"},"/ev",{"temp=":"$r"},{"->":".^.^.2.s"},[{"#n":"$r2"}],"\n",{"->":"MATH_QUEST_START"},{"#f":5}],"c-1":["ev",{"^->":"I_Get_It.0.c-1.$r2"},"/ev",{"temp=":"$r"},{"->":".^.^.3.s"},[{"#n":"$r2"}],"\n",{"->":"Unsure"},{"#f":5}]}],{"#f":1}],"MATH_QUEST_START":[["^That's the spirit! Since you’re interested in math, let’s test your skills with a quick question.","\n","^What is the answer to this: 5 + 3 x 2?","\n",["ev",{"^->":"MATH_QUEST_START.0.4.$r1"},{"temp=":"$r"},"str",{"->":".^.s"},[{"#n":"$r1"}],"/str","/ev",{"*":".^.^.c-0","flg":18},{"s":["^11",{"->":"$r","var":true},null]}],["ev",{"^->":"MATH_QUEST_START.0.5.$r1"},{"temp=":"$r"},"str",{"->":".^.s"},[{"#n":"$r1"}],"/str","/ev",{"*":".^.^.c-1","flg":18},{"s":["^16",{"->":"$r","var":true},null]}],["ev",{"^->":"MATH_QUEST_START.0.6.$r1"},{"temp=":"$r"},"str",{"->":".^.s"},[{"#n":"$r1"}],"/str","/ev",{"*":".^.^.c-2","flg":18},{"s":["^13",{"->":"$r","var":true},null]}],{"c-0":["ev",{"^->":"MATH_QUEST_START.0.c-0.$r2"},"/ev",{"temp=":"$r"},{"->":".^.^.4.s"},[{"#n":"$r2"}],"\n",{"->":"Correct_Answer"},{"#f":5}],"c-1":["ev",{"^->":"MATH_QUEST_START.0.c-1.$r2"},"/ev",{"temp=":"$r"},{"->":".^.^.5.s"},[{"#n":"$r2"}],"\n",{"->":"Incorrect_Answer"},{"#f":5}],"c-2":["ev",{"^->":"MATH_QUEST_START.0.c-2.$r2"},"/ev",{"temp=":"$r"},{"->":".^.^.6.s"},[{"#n":"$r2"}],"\n",{"->":"Incorrect_Answer"},{"#f":5}]}],{"#f":1}],"Correct_Answer":["^Well done! You’ve got a good understanding of math fundamentals. Keep practicing like this, and it will help you in many areas of life.","\n",{"->":"MathQuestCompleted"},{"#f":1}],"Incorrect_Answer":["^Close, but remember the order of operations. Multiplication comes before addition, so the correct answer was 11.","\n",{"->":"MathQuestCompleted"},{"#f":1}],"MathQuestCompleted":["ev",true,"/ev",{"VAR=":"teacherQuestCompleted","re":true},"ev",{"VAR?":"EduStat"},1,"+",{"VAR=":"EduStat","re":true},"/ev","^You completed the Math Focus quest and gained a deeper understanding of math. Keep up the hard work, and don’t hesitate to come back if you have more questions.","\n","end",{"#f":1}],"Unsure":["^You don’t need to have it all figured out yet, but keep pushing forward.","\n","end",{"#f":1}],"Waste_Of_Time":[["^A waste? You think the streets will give you a better future? Where do you think you’ll end up if you don’t commit to your education?","\n",["ev",{"^->":"Waste_Of_Time.0.2.$r1"},{"temp=":"$r"},"str",{"->":".^.s"},[{"#n":"$r1"}],"/str","/ev",{"*":".^.^.c-0","flg":18},{"s":["^I guess I’ll end up like everyone else around here, stuck.",{"->":"$r","var":true},null]}],["ev",{"^->":"Waste_Of_Time.0.3.$r1"},{"temp=":"$r"},"str",{"->":".^.s"},[{"#n":"$r1"}],"/str","/ev",{"*":".^.^.c-1","flg":18},{"s":["^I’m just trying to survive, miss.",{"->":"$r","var":true},null]}],{"c-0":["ev",{"^->":"Waste_Of_Time.0.c-0.$r2"},"/ev",{"temp=":"$r"},{"->":".^.^.2.s"},[{"#n":"$r2"}],"\n",{"->":"Stuck"},{"#f":5}],"c-1":["ev",{"^->":"Waste_Of_Time.0.c-1.$r2"},"/ev",{"temp=":"$r"},{"->":".^.^.3.s"},[{"#n":"$r2"}],"\n",{"->":"Survive"},{"#f":5}]}],{"#f":1}],"Stuck":["^That’s exactly what will happen if you don’t change your mindset.","\n","end",{"#f":1}],"Survive":["^Surviving isn’t enough. You have to think about what comes next.","\n","end",{"#f":1}],"Hard_To_Stay_Motivated":[["^I get that. Motivation isn’t always easy to find, but you need to push through. What’s been holding you back?","\n",["ev",{"^->":"Hard_To_Stay_Motivated.0.2.$r1"},{"temp=":"$r"},"str",{"->":".^.s"},[{"#n":"$r1"}],"/str","/ev",{"*":".^.^.c-0","flg":18},{"s":["^It’s hard to see the point sometimes.",{"->":"$r","var":true},null]}],["ev",{"^->":"Hard_To_Stay_Motivated.0.3.$r1"},{"temp=":"$r"},"str",{"->":".^.s"},[{"#n":"$r1"}],"/str","/ev",{"*":".^.^.c-1","flg":18},{"s":["^I feel overwhelmed by everything.",{"->":"$r","var":true},null]}],{"c-0":["ev",{"^->":"Hard_To_Stay_Motivated.0.c-0.$r2"},"/ev",{"temp=":"$r"},{"->":".^.^.2.s"},[{"#n":"$r2"}],"\n",{"->":"Hard_To_See_Point"},{"#f":5}],"c-1":["ev",{"^->":"Hard_To_Stay_Motivated.0.c-1.$r2"},"/ev",{"temp=":"$r"},{"->":".^.^.3.s"},[{"#n":"$r2"}],"\n",{"->":"Overwhelmed"},{"#f":5}]}],{"#f":1}],"Hard_To_See_Point":["^If you can’t see the point, then you need to change your perspective.","\n","end",{"#f":1}],"Overwhelmed":["^That’s normal, but don’t let it stop you from moving forward.","\n","end",{"#f":1}],"AddEdu":["ev",{"VAR?":"EduStat"},1,"+",{"VAR=":"EduStat","re":true},"/ev","ev",{"VAR?":"GangStat"},1,"-",0,"MIN","/ev",{"VAR=":"GangStat","re":true},"\n","end",{"#f":1}],"AddGang":["ev",{"VAR?":"GangStat"},1,"+",{"VAR=":"GangStat","re":true},"/ev","ev",{"VAR?":"EduStat"},1,"-",0,"MIN","/ev",{"VAR=":"EduStat","re":true},"\n","end",{"#f":1}],"global decl":["ev",0,{"VAR=":"EduStat"},0,{"VAR=":"GangStat"},false,{"VAR=":"supportQuestStarted"},false,{"VAR=":"dreamsQuestStarted"},false,{"VAR=":"honestyQuestStarted"},false,{"VAR=":"familyQuestStarted"},false,{"VAR=":"roleModelQuestStarted"},false,{"VAR=":"trustQuestCompleted"},false,{"VAR=":"choicesQuestStarted"},false,{"VAR=":"gangQuestStarted"},false,{"VAR=":"gangQuestCompleted"},false,{"VAR=":"influenceQuestStarted"},false,{"VAR=":"troubleQuestStarted"},false,{"VAR=":"standingFirmQuestStarted"},false,{"VAR=":"teacherQuestStarted"},false,{"VAR=":"teacherQuestCompleted"},false,{"VAR=":"studyMentorSpawned"},false,{"VAR=":"empathyQuestStarted"},false,{"VAR=":"empathyQuestCompleted"},false,{"VAR=":"emotionalQuestCompleted"},false,{"VAR=":"timeManagementQuestCompleted"},false,{"VAR=":"teacherPriorityQuestCompleted"},false,{"VAR=":"teacherPriorityQuestStarted"},false,{"VAR=":"teacherGoalQuestStarted"},false,{"VAR=":"teacherGoalQuestCompleted"},false,{"VAR=":"conflictResolutionQuestStarted"},false,{"VAR=":"conflictResolutionQuestCompleted"},false,{"VAR=":"lifeChoicesQuestStarted"},false,{"VAR=":"lifeChoicesQuestCompleted"},false,{"VAR=":"healthyChoicesQuestStarted"},false,{"VAR=":"healthyChoicesQuestCompleted"},false,{"VAR=":"constructiveCriticismQuestStarted"},false,{"VAR=":"constructiveCriticismQuestCompleted"},false,{"VAR=":"smallWinsQuestStarted"},false,{"VAR=":"smallWinsQuestCompleted"},false,{"VAR=":"stayFocusedQuestStarted"},false,{"VAR=":"stayFocusedQuestCompleted"},false,{"VAR=":"communityQuestStarted"},false,{"VAR=":"communityQuestCompleted"},"/ev","end",null],"#f":1}],"listDefs":{}}